{
  "id": "88275326-a3fc-4527-ae6b-4f0c7553eb8e",
  "algorithm": "",
  "fromVersionId": "none",
  "toVersionId": "v1.0.0-bootstrap",
  "promotedAt": "2025-10-17T12:03:37.6676749Z",
  "promotedBy": "",
  "reason": "Bootstrap: Initial champion registration",
  "validationReportPath": "",
  "passedValidation": false,
  "performanceImprovement": 0,
  "riskReduction": 0,
  "wasRolledBack": false,
  "rolledBackAt": null,
  "rollbackReason": "",
  "wasFlat": false,
  "marketSession": "",
  "contextData": {}
}